docx/__init__.py
docx/api.py
docx/blkcntnr.py
docx/compat.py
docx/document.py
docx/exceptions.py
docx/package.py
docx/section.py
docx/settings.py
docx/shape.py
docx/shared.py
docx/table.py
docx/dml/__init__.py
docx/dml/color.py
docx/enum/__init__.py
docx/enum/base.py
docx/enum/dml.py
docx/enum/section.py
docx/enum/shape.py
docx/enum/style.py
docx/enum/table.py
docx/enum/text.py
docx/image/__init__.py
docx/image/bmp.py
docx/image/constants.py
docx/image/emf.py
docx/image/exceptions.py
docx/image/gif.py
docx/image/helpers.py
docx/image/image.py
docx/image/jpeg.py
docx/image/png.py
docx/image/tiff.py
docx/opc/__init__.py
docx/opc/compat.py
docx/opc/constants.py
docx/opc/coreprops.py
docx/opc/exceptions.py
docx/opc/oxml.py
docx/opc/package.py
docx/opc/packuri.py
docx/opc/part.py
docx/opc/phys_pkg.py
docx/opc/pkgreader.py
docx/opc/pkgwriter.py
docx/opc/rel.py
docx/opc/shared.py
docx/opc/spec.py
docx/opc/parts/__init__.py
docx/opc/parts/coreprops.py
docx/oxml/__init__.py
docx/oxml/comments.py
docx/oxml/coreprops.py
docx/oxml/document.py
docx/oxml/exceptions.py
docx/oxml/footnotes.py
docx/oxml/ns.py
docx/oxml/numbering.py
docx/oxml/section.py
docx/oxml/settings.py
docx/oxml/shape.py
docx/oxml/shared.py
docx/oxml/simpletypes.py
docx/oxml/styles.py
docx/oxml/table.py
docx/oxml/xmlchemy.py
docx/oxml/text/__init__.py
docx/oxml/text/font.py
docx/oxml/text/paragraph.py
docx/oxml/text/parfmt.py
docx/oxml/text/run.py
docx/parts/__init__.py
docx/parts/comments.py
docx/parts/document.py
docx/parts/footnotes.py
docx/parts/hdrftr.py
docx/parts/image.py
docx/parts/numbering.py
docx/parts/settings.py
docx/parts/story.py
docx/parts/styles.py
docx/styles/__init__.py
docx/styles/latent.py
docx/styles/style.py
docx/styles/styles.py
docx/templates/default-comments.xml
docx/templates/default-footer.xml
docx/templates/default-footnotes.xml
docx/templates/default-header.xml
docx/templates/default-settings.xml
docx/templates/default-styles.xml
docx/templates/default.docx
docx/text/__init__.py
python_docx_2023-0.2.17.dist-info/LICENSE
python_docx_2023-0.2.17.dist-info/METADATA
python_docx_2023-0.2.17.dist-info/WHEEL
python_docx_2023-0.2.17.dist-info/top_level.txt
python_docx_2023-0.2.17.dist-info/RECORD
