Metadata-Version: 2.1
Name: python-docx-2023
Version: 0.2.17
Summary: Create and update Microsoft Word .docx files.
Home-page: https://github.com/idtareq/python-docx-2023
Author: Tareq Ibrahim
Author-email: idtareq@gmail.com
License: The MIT License (MIT)
Keywords: docx office openxml word
Classifier: Development Status :: 3 - Alpha
Classifier: Environment :: Console
Classifier: Intended Audience :: Developers
Classifier: License :: OSI Approved :: MIT License
Classifier: Operating System :: OS Independent
Classifier: Programming Language :: Python
Classifier: Programming Language :: Python :: 2
Classifier: Programming Language :: Python :: 2.6
Classifier: Programming Language :: Python :: 2.7
Classifier: Programming Language :: Python :: 3
Classifier: Programming Language :: Python :: 3.3
Classifier: Programming Language :: Python :: 3.4
Classifier: Topic :: Office/Business :: Office Suites
Classifier: Topic :: Software Development :: Libraries
License-File: LICENSE
Requires-Dist: lxml (>=2.3.2)
